instrumentor/__init__.py
instrumentor/example.py
instrumentor/exposition.py
instrumentor/metrics.py
instrumentor/registry.py
instrumentor-0.0.1.dist-info/LICENSE
instrumentor-0.0.1.dist-info/METADATA
instrumentor-0.0.1.dist-info/WHEEL
instrumentor-0.0.1.dist-info/top_level.txt
instrumentor-0.0.1.dist-info/RECORD
