Metadata-Version: 2.1
Name: instrumentor
Version: 0.0.1
Summary: Instrumentation library for python apps. Backed by Redis and exposes to Prometheus
Home-page: https://github.com/u9n/instrumentor
Author: Henrik Palmlund Wahlgren @ Palmlund Wahlgren Innovative Technology AB
Author-email: henrik@pwit.se
License: BSD-3
Platform: UNKNOWN
Classifier: Development Status :: 3 - Alpha
Classifier: License :: OSI Approved :: BSD License
Classifier: Natural Language :: English
Classifier: Programming Language :: Python
Classifier: Programming Language :: Python :: 3
Classifier: Programming Language :: Python :: 3 :: Only
Classifier: Programming Language :: Python :: 3.6
Classifier: Topic :: Software Development :: Libraries
Requires-Python: >=3.6
Requires-Dist: redis (==3.3.7)
Requires-Dist: hiredis (==1.0.0)
Requires-Dist: attrs (==19.1.0)
